LICENSE
README.md
setup.py
demo/__init__.py
demo/__main__.py
demo/cli.py
demo/throttle.py
funktools/__init__.py
funktools/_base.py
funktools/_cli.py
funktools/_log.py
funktools/_lru_cache.py
funktools/_noop.py
funktools/_retry.py
funktools/_sqlite_cache.py
funktools/_template.py
funktools/_throttle.py
funktools.egg-info/PKG-INFO
funktools.egg-info/SOURCES.txt
funktools.egg-info/dependency_links.txt
funktools.egg-info/requires.txt
funktools.egg-info/top_level.txt
test/__init__.py
test/test_base.py
test/test_cli.py
test/test_lru_cache.py
test/test_retry.py
test/test_sqlite_cache.py
test/test_template.py
test/test_throttle.py